{"language":"none","metadata":{"display_name":"iPhone用数字テンキー","custard_version":"1.2"},"input_style":"direct","interface":{"keys":[{"key_type":"custom","specifier":{"y":4,"x":1,"width":1,"height":1},"key":{"design":{"label":{"text":"年月日"},"color":"normal"},"variations":[{"key":{"press_actions":[{"type":"input","text":"年"}],"longpress_actions":{"start":[],"repeat":[]},"design":{"label":{"text":"年"}}},"type":"flick_variation","direction":"left"},{"key":{"press_actions":[{"type":"input","text":"月"}],"longpress_actions":{"start":[],"repeat":[]},"design":{"label":{"text":"月"}}},"type":"flick_variation","direction":"top"},{"key":{"press_actions":[{"type":"input","text":"日"}],"longpress_actions":{"start":[],"repeat":[]},"design":{"label":{"text":"日"}}},"type":"flick_variation","direction":"right"}],"press_actions":[{"type":"input","text":"年"}],"longpress_actions":{"start":[],"repeat":[]}},"specifier_type":"grid_fit"},{"key_type":"custom","specifier":{"y":0,"x":2,"width":2,"height":2},"key":{"design":{"label":{"text":"1"},"color":"normal"},"variations":[],"press_actions":[{"type":"input","text":"1"},{"type":"complete"}],"longpress_actions":{"start":[],"repeat":[]}},"specifier_type":"grid_fit"},{"key_type":"custom","specifier":{"y":2,"x":1,"width":1,"height":1},"key":{"design":{"label":{"text":"-"},"color":"normal"},"variations":[{"key":{"press_actions":[{"type":"input","text":"="}],"longpress_actions":{"start":[],"repeat":[]},"design":{"label":{"text":"="}}},"type":"flick_variation","direction":"right"},{"key":{"press_actions":[{"type":"input","text":"_"}],"longpress_actions":{"start":[],"repeat":[]},"design":{"label":{"text":"_"}}},"type":"flick_variation","direction":"left"},{"key":{"press_actions":[{"type":"input","text":"~"}],"longpress_actions":{"start":[],"repeat":[]},"design":{"label":{"text":"~"}}},"type":"flick_variation","direction":"top"}],"press_actions":[{"type":"input","text":"-"}],"longpress_actions":{"start":[],"repeat":[]}},"specifier_type":"grid_fit"},{"key_type":"custom","specifier":{"y":4,"x":6,"width":2,"height":2},"key":{"design":{"label":{"text":"9"},"color":"normal"},"variations":[],"press_actions":[{"type":"input","text":"9"},{"type":"complete"}],"longpress_actions":{"start":[],"repeat":[]}},"specifier_type":"grid_fit"},{"key_type":"custom","specifier":{"y":6,"x":4,"width":2,"height":2},"key":{"design":{"label":{"text":"0"},"color":"normal"},"variations":[],"press_actions":[{"type":"input","text":"0"},{"type":"complete"}],"longpress_actions":{"start":[],"repeat":[]}},"specifier_type":"grid_fit"},{"key_type":"custom","specifier":{"y":6,"x":2,"width":2,"height":2},"key":{"design":{"label":{"text":","},"color":"normal"},"variations":[{"key":{"press_actions":[{"type":"input","text":"、"}],"longpress_actions":{"start":[],"repeat":[]},"design":{"label":{"text":"、"}}},"type":"flick_variation","direction":"right"},{"key":{"press_actions":[{"type":"input","text":"、"}],"longpress_actions":{"start":[],"repeat":[]},"design":{"label":{"text":"、"}}},"type":"flick_variation","direction":"left"}],"press_actions":[{"type":"input","text":","},{"type":"complete"}],"longpress_actions":{"start":[],"repeat":[]}},"specifier_type":"grid_fit"},{"key_type":"custom","specifier":{"y":5,"x":1,"width":1,"height":1},"key":{"design":{"label":{"text":"円¥$"},"color":"normal"},"variations":[{"key":{"press_actions":[{"type":"input","text":"円"}],"longpress_actions":{"start":[],"repeat":[]},"design":{"label":{"text":"円"}}},"type":"flick_variation","direction":"left"},{"key":{"press_actions":[{"type":"input","text":"¥"}],"longpress_actions":{"start":[],"repeat":[]},"design":{"label":{"text":"¥"}}},"type":"flick_variation","direction":"top"},{"key":{"press_actions":[{"type":"input","text":"$"}],"longpress_actions":{"start":[],"repeat":[]},"design":{"label":{"text":"$"}}},"type":"flick_variation","direction":"right"}],"press_actions":[{"type":"input","text":"円"}],"longpress_actions":{"start":[],"repeat":[]}},"specifier_type":"grid_fit"},{"key_type":"custom","specifier":{"y":4,"x":4,"width":2,"height":2},"key":{"design":{"label":{"text":"8"},"color":"normal"},"variations":[],"press_actions":[{"type":"input","text":"8"},{"type":"complete"}],"longpress_actions":{"start":[],"repeat":[]}},"specifier_type":"grid_fit"},{"key_type":"custom","specifier":{"y":2,"x":8,"width":2,"height":2},"key":{"design":{"label":{"text":"空白"},"color":"special"},"variations":[{"key":{"press_actions":[{"type":"move_cursor","count":-1}],"longpress_actions":{"start":[],"repeat":[{"type":"move_cursor","count":-1}]},"design":{"label":{"text":"←"}}},"type":"flick_variation","direction":"left"},{"key":{"press_actions":[{"type":"input","text":"　"}],"longpress_actions":{"start":[],"repeat":[]},"design":{"label":{"text":"全角"}}},"type":"flick_variation","direction":"top"},{"key":{"press_actions":[{"type":"input","text":"\t"}],"longpress_actions":{"start":[],"repeat":[]},"design":{"label":{"text":"tab"}}},"type":"flick_variation","direction":"bottom"}],"press_actions":[{"type":"input","text":" "}],"longpress_actions":{"start":[{"type":"toggle_cursor_bar"}],"repeat":[]}},"specifier_type":"grid_fit"},{"key_type":"custom","specifier":{"y":2,"x":0,"width":1,"height":1},"key":{"design":{"label":{"text":"+℃"},"color":"normal"},"variations":[{"key":{"press_actions":[{"type":"input","text":"℃"},{"type":"complete"}],"longpress_actions":{"start":[],"repeat":[]},"design":{"label":{"text":"℃"}}},"type":"flick_variation","direction":"right"},{"key":{"press_actions":[{"type":"input","text":"°"}],"longpress_actions":{"start":[],"repeat":[]},"design":{"label":{"text":"°"}}},"type":"flick_variation","direction":"top"}],"press_actions":[{"type":"input","text":"+"}],"longpress_actions":{"start":[],"repeat":[]}},"specifier_type":"grid_fit"},{"key_type":"custom","specifier":{"y":0,"x":8,"width":2,"height":2},"key":{"design":{"label":{"system_image":"delete.left"},"color":"special"},"variations":[{"key":{"press_actions":[{"type":"smart_delete_default"}],"longpress_actions":{"start":[],"repeat":[]},"design":{"label":{"system_image":"xmark"}}},"type":"flick_variation","direction":"left"}],"press_actions":[{"type":"delete","count":1}],"longpress_actions":{"start":[],"repeat":[{"type":"delete","count":1}]}},"specifier_type":"grid_fit"},{"key_type":"custom","specifier":{"y":0,"x":0,"width":1,"height":2},"key":{"design":{"label":{"text":"←"},"color":"special"},"variations":[],"press_actions":[{"type":"move_cursor","count":-1}],"longpress_actions":{"start":[],"repeat":[{"type":"move_cursor","count":-1}]}},"specifier_type":"grid_fit"},{"key_type":"custom","specifier":{"y":2,"x":2,"width":2,"height":2},"key":{"design":{"label":{"text":"4"},"color":"normal"},"variations":[],"press_actions":[{"type":"input","text":"4"},{"type":"complete"}],"longpress_actions":{"start":[],"repeat":[]}},"specifier_type":"grid_fit"},{"key_type":"custom","specifier":{"y":5,"x":0,"width":1,"height":1},"key":{"design":{"label":{"text":"( )"},"color":"normal"},"variations":[{"key":{"press_actions":[{"type":"input","text":"("}],"longpress_actions":{"start":[],"repeat":[]},"design":{"label":{"text":"("}}},"type":"flick_variation","direction":"left"},{"key":{"press_actions":[{"type":"input","text":")"}],"longpress_actions":{"start":[],"repeat":[]},"design":{"label":{"text":")"}}},"type":"flick_variation","direction":"right"}],"press_actions":[{"type":"input","text":"("}],"longpress_actions":{"start":[],"repeat":[]}},"specifier_type":"grid_fit"},{"key_type":"custom","specifier":{"y":6,"x":0,"width":1,"height":2},"key":{"design":{"label":{"text":"abc"},"color":"special"},"variations":[],"press_actions":[{"type":"move_tab","tab_type":"custom","identifier":"iPhone用英数小文字アルファベット順"}],"longpress_actions":{"start":[],"repeat":[]}},"specifier_type":"grid_fit"},{"key_type":"custom","specifier":{"y":6,"x":1,"width":1,"height":2},"key":{"design":{"label":{"text":"あいう"},"color":"special"},"variations":[],"press_actions":[{"type":"move_tab","tab_type":"custom","identifier":"iPhone用かな五十音順"}],"longpress_actions":{"start":[],"repeat":[]}},"specifier_type":"grid_fit"},{"key_type":"custom","specifier":{"y":2,"x":4,"width":2,"height":2},"key":{"design":{"label":{"text":"5"},"color":"normal"},"variations":[],"press_actions":[{"type":"input","text":"5"},{"type":"complete"}],"longpress_actions":{"start":[],"repeat":[]}},"specifier_type":"grid_fit"},{"key_type":"custom","specifier":{"y":4,"x":2,"width":2,"height":2},"key":{"design":{"label":{"text":"7"},"color":"normal"},"variations":[],"press_actions":[{"type":"input","text":"7"},{"type":"complete"}],"longpress_actions":{"start":[],"repeat":[]}},"specifier_type":"grid_fit"},{"key_type":"custom","specifier":{"y":2,"x":6,"width":2,"height":2},"key":{"design":{"label":{"text":"6"},"color":"normal"},"variations":[],"press_actions":[{"type":"input","text":"6"},{"type":"complete"}],"longpress_actions":{"start":[],"repeat":[]}},"specifier_type":"grid_fit"},{"key_type":"custom","specifier":{"y":3,"x":1,"width":1,"height":1},"key":{"design":{"label":{"text":"\/"},"color":"normal"},"variations":[{"key":{"press_actions":[{"type":"input","text":"÷"}],"longpress_actions":{"start":[],"repeat":[]},"design":{"label":{"text":"÷"}}},"type":"flick_variation","direction":"right"},{"key":{"press_actions":[{"type":"input","text":"\\"}],"longpress_actions":{"start":[],"repeat":[]},"design":{"label":{"text":"\\"}}},"type":"flick_variation","direction":"left"},{"key":{"press_actions":[{"type":"input","text":"%"}],"longpress_actions":{"start":[],"repeat":[]},"design":{"label":{"text":"%"}}},"type":"flick_variation","direction":"top"},{"key":{"press_actions":[{"type":"input","text":"|"}],"longpress_actions":{"start":[],"repeat":[]},"design":{"label":{"text":"|"}}},"type":"flick_variation","direction":"bottom"}],"press_actions":[{"type":"input","text":"\/"}],"longpress_actions":{"start":[],"repeat":[]}},"specifier_type":"grid_fit"},{"key_type":"custom","specifier":{"y":0,"x":1,"width":1,"height":2},"key":{"design":{"label":{"text":"→"},"color":"special"},"variations":[],"press_actions":[{"type":"move_cursor","count":1}],"longpress_actions":{"start":[],"repeat":[{"type":"move_cursor","count":1}]}},"specifier_type":"grid_fit"},{"key_type":"custom","specifier":{"y":3,"x":0,"width":1,"height":1},"key":{"design":{"label":{"text":"*"},"color":"normal"},"variations":[{"key":{"press_actions":[{"type":"input","text":"×"}],"longpress_actions":{"start":[],"repeat":[]},"design":{"label":{"text":"×"}}},"type":"flick_variation","direction":"left"},{"key":{"press_actions":[{"type":"input","text":"×"}],"longpress_actions":{"start":[],"repeat":[]},"design":{"label":{"text":"×"}}},"type":"flick_variation","direction":"right"}],"press_actions":[{"type":"input","text":"*"}],"longpress_actions":{"start":[],"repeat":[]}},"specifier_type":"grid_fit"},{"key_type":"custom","specifier":{"y":0,"x":4,"width":2,"height":2},"key":{"design":{"label":{"text":"2"},"color":"normal"},"variations":[],"press_actions":[{"type":"input","text":"2"},{"type":"complete"}],"longpress_actions":{"start":[],"repeat":[]}},"specifier_type":"grid_fit"},{"key_type":"custom","specifier":{"y":4,"x":0,"width":1,"height":1},"key":{"design":{"label":{"text":":"},"color":"normal"},"variations":[{"key":{"press_actions":[{"type":"input","text":"分"}],"longpress_actions":{"start":[],"repeat":[]},"design":{"label":{"text":"分"}}},"type":"flick_variation","direction":"right"},{"key":{"press_actions":[{"type":"input","text":"時"}],"longpress_actions":{"start":[],"repeat":[]},"design":{"label":{"text":"時"}}},"type":"flick_variation","direction":"top"},{"key":{"press_actions":[{"type":"input","text":"秒"}],"longpress_actions":{"start":[],"repeat":[]},"design":{"label":{"text":"秒"}}},"type":"flick_variation","direction":"bottom"}],"press_actions":[{"type":"input","text":":"}],"longpress_actions":{"start":[],"repeat":[]}},"specifier_type":"grid_fit"},{"key_type":"system","specifier":{"y":4,"x":8,"width":2,"height":4},"key":{"type":"enter"},"specifier_type":"grid_fit"},{"key_type":"custom","specifier":{"y":0,"x":6,"width":2,"height":2},"key":{"design":{"label":{"text":"3"},"color":"normal"},"variations":[],"press_actions":[{"type":"input","text":"3"},{"type":"complete"}],"longpress_actions":{"start":[],"repeat":[]}},"specifier_type":"grid_fit"},{"key_type":"custom","specifier":{"y":6,"x":6,"width":2,"height":2},"key":{"design":{"label":{"text":"."},"color":"normal"},"variations":[{"key":{"press_actions":[{"type":"input","text":"。"}],"longpress_actions":{"start":[],"repeat":[]},"design":{"label":{"text":"。"}}},"type":"flick_variation","direction":"right"},{"key":{"press_actions":[{"type":"input","text":"。"}],"longpress_actions":{"start":[],"repeat":[]},"design":{"label":{"text":"。"}}},"type":"flick_variation","direction":"left"}],"press_actions":[{"type":"input","text":"."},{"type":"complete"}],"longpress_actions":{"start":[],"repeat":[]}},"specifier_type":"grid_fit"}],"key_style":"tenkey_style","key_layout":{"type":"grid_fit","row_count":10,"column_count":8}},"identifier":"iPhone用数字テンキー"}